link2mp4/__init__.py
link2mp4/__main__.py
link2mp4/capture.py
link2mp4/pinterest.py
link2mp4/reddit.py
link2mp4/tiktok.py
link2mp4/twitter.py
link2mp4/youtube.py
link2mp4-1.0.0.dist-info/LICENSE
link2mp4-1.0.0.dist-info/METADATA
link2mp4-1.0.0.dist-info/WHEEL
link2mp4-1.0.0.dist-info/entry_points.txt
link2mp4-1.0.0.dist-info/top_level.txt
link2mp4-1.0.0.dist-info/RECORD
