Metadata-Version: 2.1
Name: link2mp4
Version: 1.0.0
Summary: Download videos as MP4 files
Home-page: https://github.com/Hamagnivim/link2mp4
Author: Elisha Hollander
Author-email: just4now666666@gmail.com
License: MIT
Project-URL: Documentation, https://github.com/Hamagnivim/link2mp4#readme
Project-URL: Bug Reports, https://github.com/Hamagnivim/link2mp4/issues
Project-URL: Source Code, https://github.com/Hamagnivim/link2mp4
Platform: UNKNOWN
Classifier: Programming Language :: Python :: 3
Requires-Python: >=3.0
License-File: LICENSE
Requires-Dist: selenium (>=4.1.0)
Requires-Dist: selenium-wire (>=4.6.4)
Requires-Dist: moviepy (>=1.0.3)
Requires-Dist: questionary (>=1.10.0)
Requires-Dist: m3u8 (>=2.0.0)
